messenger/__init__.py
messenger/messenger.py
messenger/subscriber.py
mpa/__init__.py
mpa/consumer.py
mpa/processor.py
mpa/producer.py
mpa/examples/__init__.py
mpa/examples/config.py
mpa/examples/mpa_consumer.py
mpa/examples/mpa_processor.py
mpa/examples/mpa_producer.py
mpa/tests/__init__.py
mpa/tests/config_test.py
mpa/tests/test_consumer.py
mpa/tests/test_processor.py
mpa/tests/test_producer.py
nats_messenger/__init__.py
nats_messenger/messenger.py
nats_messenger/subscriber.py
nats_messenger/tests/__init__.py
nats_messenger/tests/config_test.py
nats_messenger/tests/test_durable_messenger.py
nats_messenger/tests/test_non_durable_messenger.py
rpc/__init__.py
rpc/client.py
rpc/server.py
rpc/examples/__init__.py
rpc/examples/config.py
rpc/examples/rpc_client.py
rpc/examples/rpc_server.py
py_msgp-1.2.0.dist-info/LICENSE
py_msgp-1.2.0.dist-info/METADATA
py_msgp-1.2.0.dist-info/WHEEL
py_msgp-1.2.0.dist-info/top_level.txt
py_msgp-1.2.0.dist-info/RECORD
